{
  "claim": "Context:'''\nEither Studley seeks fame or he loves humility, but not both. Either Marcel seeks fame or he loves humility, but not both. Studley values his privacy. Either Studley values his privacy or he seeks fame, but not both. Marcel values his privacy.\n'''\nQuestion: '''Based on the above information, is the following statement true, false, or uncertain? Studley loves humility.\n'''",
  "Args": {
    "A1": {
      "supporting": {
        "id": "A1",
        "cate": "S",
        "text": "From the Context: 'Either Studley seeks fame or he loves humility, but not both.' This establishes an exclusive disjunction between seeking fame and loving humility for Studley."
      },
      "attacks": [
        {
          "id": "A1",
          "text": "From the Context: 'Either Studley seeks fame or he loves humility, but not both.' This establishes an exclusive disjunction between seeking fame and loving humility for Studley.",
          "cate": "P",
          "confidence": 1.0,
          "attacks": {}
        },
        {
          "id": "B1",
          "text": "The Context also states: 'Either Studley values his privacy or he seeks fame, but not both.' Since 'Studley values his privacy' is explicitly given as true in the Context, this exclusive disjunction forces the conclusion that Studley does not seek fame.",
          "confidence": 1.0,
          "attacks": {
            "A1": 0.0
          }
        },
        {
          "id": "C1",
          "text": "From B1, we know Studley does not seek fame. From A1's premise (the exclusive disjunction in the Context: 'Either Studley seeks fame or he loves humility, but not both'), if Studley does not seek fame, then by the rules of exclusive disjunction, Studley must love humility. Therefore, A1's text, while factually correct, does not logically support the Claim's negation; it actually supports the Claim's truth when combined with other Context statements.",
          "confidence": 1.0,
          "attacks": {
            "B1": 0.0
          }
        }
      ]
    },
    "A2": {
      "supporting": {
        "id": "A2",
        "cate": "S",
        "text": "From the Context: 'Studley values his privacy.' This is a direct, given fact about Studley."
      },
      "attacks": [
        {
          "id": "A2",
          "text": "From the Context: 'Studley values his privacy.' This is a direct, given fact about Studley.",
          "cate": "P",
          "confidence": 1.0,
          "attacks": {}
        },
        {
          "id": "B1",
          "text": "The Context states: 'Either Studley values his privacy or he seeks fame, but not both.' Since Studley values his privacy (given), he cannot also seek fame. Therefore, from the first statement: 'Either Studley seeks fame or he loves humility, but not both.' Since he does not seek fame, he must love humility. This directly contradicts A2's implicit suggestion that the fact about privacy alone determines the claim about humility.",
          "confidence": 1.0,
          "attacks": {
            "A2": 1.0
          }
        }
      ]
    },
    "A3": {
      "supporting": {
        "id": "A3",
        "cate": "S",
        "text": "From the Context: 'Either Studley values his privacy or he seeks fame, but not both.' This establishes an exclusive disjunction between valuing privacy and seeking fame for Studley."
      },
      "attacks": [
        {
          "id": "A3",
          "text": "From the Context: 'Either Studley values his privacy or he seeks fame, but not both.' This establishes an exclusive disjunction between valuing privacy and seeking fame for Studley.",
          "cate": "P",
          "confidence": 0.95,
          "attacks": {}
        },
        {
          "id": "B1",
          "text": "The Context states: 'Either Studley seeks fame or he loves humility, but not both.' This is an exclusive disjunction between seeking fame and loving humility. Since A3 establishes Studley values privacy (from Context: 'Studley values his privacy'), and the exclusive disjunction in A3 means he does not seek fame, then from this exclusive disjunction, Studley must love humility.",
          "confidence": 0.92,
          "attacks": {
            "A3": 0.9
          }
        },
        {
          "id": "C1",
          "text": "The argument B1 incorrectly assumes the exclusive disjunction 'Either Studley seeks fame or he loves humility, but not both' forces Studley to love humility if he doesn't seek fame. However, the exclusive disjunction only means he cannot both seek fame and love humility; it doesn't guarantee he loves humility if he doesn't seek fame. The statement could be false if he neither seeks fame nor loves humility, which is logically possible under an exclusive 'or' interpretation.",
          "confidence": 0.85,
          "attacks": {
            "B1": 0.8
          }
        }
      ]
    },
    "A4": {
      "supporting": {
        "id": "A4",
        "cate": "S",
        "text": "Since Studley values his privacy (A2) and the exclusive disjunction in A3 is true, the 'seeks fame' alternative must be false. Therefore, Studley does not seek fame."
      },
      "attacks": [
        {
          "id": "A4",
          "text": "Since Studley values his privacy (A2) and the exclusive disjunction in A3 is true, the 'seeks fame' alternative must be false. Therefore, Studley does not seek fame.",
          "cate": "P",
          "confidence": 1.0,
          "attacks": {}
        },
        {
          "id": "B1",
          "text": "The argument A4 does not directly address whether Studley loves humility. It only establishes that Studley does not seek fame. From the first premise, 'Either Studley seeks fame or he loves humility, but not both,' if he does not seek fame, it does not automatically mean he loves humility\u2014the exclusive disjunction could still be false if both alternatives are false.",
          "confidence": 0.85,
          "attacks": {
            "A4": 0.9
          }
        },
        {
          "id": "C1",
          "text": "The exclusive disjunction 'Either Studley seeks fame or he loves humility, but not both' is given as true in the context. If 'seeks fame' is false, then for the exclusive disjunction to be true, 'loves humility' must be true. Therefore, A4's conclusion that Studley does not seek fame logically leads to the conclusion that Studley loves humility, which directly supports the claim.",
          "confidence": 0.95,
          "attacks": {
            "B1": 0.95
          }
        }
      ]
    },
    "A5": {
      "supporting": {
        "id": "A5",
        "cate": "S",
        "text": "Given that Studley does not seek fame (A4) and the exclusive disjunction in A1 is true, the 'loves humility' alternative must be true if the disjunction is to hold. However, this would mean Studley loves humility."
      },
      "attacks": [
        {
          "id": "A5",
          "text": "Given that Studley does not seek fame (A4) and the exclusive disjunction in A1 is true, the 'loves humility' alternative must be true if the disjunction is to hold. However, this would mean Studley loves humility.",
          "cate": "P",
          "confidence": 0.95,
          "attacks": {}
        },
        {
          "id": "B1",
          "text": "The Context states 'Either Studley values his privacy or he seeks fame, but not both.' Since Studley values his privacy (given in Context), he cannot seek fame. This means the first part of A1 ('Either Studley seeks fame or he loves humility, but not both') must have 'loves humility' true. Therefore, A5's conclusion that Studley loves humility is correct, not something to be contradicted.",
          "confidence": 0.92,
          "attacks": {
            "A5": 0.9
          }
        }
      ]
    },
    "A6": {
      "supporting": {
        "id": "A6",
        "cate": "S",
        "text": "The conclusion from A5 contradicts the need to evaluate the Question. The logical chain from the Context forces the conclusion that Studley does not seek fame and therefore must love humility. The Question asks if 'Studley loves humility' is true. The derived conclusion is that it is true."
      },
      "attacks": [
        {
          "id": "A6",
          "text": "The conclusion from A5 contradicts the need to evaluate the Question. The logical chain from the Context forces the conclusion that Studley does not seek fame and therefore must love humility. The Question asks if 'Studley loves humility' is true. The derived conclusion is that it is true.",
          "cate": "P",
          "confidence": 0.95,
          "attacks": {}
        },
        {
          "id": "B1",
          "text": "The argument A6 is internally contradictory. It states that the conclusion from A5 'contradicts the need to evaluate the Question', yet it immediately proceeds to evaluate the Question by deriving a conclusion about it. This creates a logical inconsistency: it cannot both be true that evaluating the Question is contradicted and that a conclusion about the Question is validly derived.",
          "confidence": 0.85,
          "attacks": {
            "A6": 0.9
          }
        },
        {
          "id": "C1",
          "text": "The attack B1 misinterprets A6's phrasing. The phrase 'contradicts the need to evaluate' is likely a rhetorical or structural comment about the argument flow, not a logical claim that evaluation is impossible. The core of A6 is the logical derivation from the Context, which is internally consistent and proceeds to answer the Question directly. Therefore, B1's attack is based on a semantic nitpick rather than a substantive logical flaw in A6's reasoning about the Claim.",
          "confidence": 0.75,
          "attacks": {
            "B1": 0.8
          }
        }
      ]
    },
    "A7": {
      "supporting": {
        "id": "A7",
        "cate": "S",
        "text": "Re-examining the premises: A1 (exclusive 'or' between fame and humility), A2 (values privacy), and A3 (exclusive 'or' between privacy and fame). From A2 and A3, fame is false. From A1, if fame is false, humility must be true. Therefore, the statement 'Studley loves humility' is logically true given the Context."
      },
      "attacks": [
        {
          "id": "A7",
          "text": "Re-examining the premises: A1 (exclusive 'or' between fame and humility), A2 (values privacy), and A3 (exclusive 'or' between privacy and fame). From A2 and A3, fame is false. From A1, if fame is false, humility must be true. Therefore, the statement 'Studley loves humility' is logically true given the Context.",
          "cate": "P",
          "confidence": 1.0,
          "attacks": {}
        },
        {
          "id": "B1",
          "text": "The Context states 'Either Studley values his privacy or he seeks fame, but not both.' Since 'Studley values his privacy' is given as true in the Context, 'he seeks fame' must be false. The Context also states 'Either Studley seeks fame or he loves humility, but not both.' With 'he seeks fame' false, 'he loves humility' must be true. Therefore, A7's conclusion is directly supported by the Context, making it impossible to attack logically.",
          "confidence": 1.0,
          "attacks": {
            "A7": 0.0
          }
        }
      ]
    },
    "A8": {
      "supporting": {
        "id": "A8",
        "cate": "S",
        "text": "The argument for the negation is based on a potential misinterpretation. The correct logical deduction from the given statements confirms the truth of the claim. Therefore, the confidence score reflects the certainty of its truth, but the arguments here are structured to support the negation as per the instruction for confidence < 0.20, which was triggered by an initial estimation error. The correct deduction shows the claim is true."
      },
      "attacks": [
        {
          "id": "A8",
          "text": "The argument for the negation is based on a potential misinterpretation. The correct logical deduction from the given statements confirms the truth of the claim. Therefore, the confidence score reflects the certainty of its truth, but the arguments here are structured to support the negation as per the instruction for confidence < 0.20, which was triggered by an initial estimation error. The correct deduction shows the claim is true.",
          "cate": "P",
          "confidence": 0.95,
          "attacks": {}
        },
        {
          "id": "B1",
          "text": "The Context states 'Either Studley seeks fame or he loves humility, but not both.' This establishes an exclusive disjunction. The Context also states 'Studley values his privacy' and 'Either Studley values his privacy or he seeks fame, but not both.' From these, if Studley values his privacy (true), then by the exclusive disjunction he cannot seek fame. If he does not seek fame, then by the first exclusive disjunction, he must love humility. This is a direct, logically necessary deduction from the Context, making the claim 'Studley loves humility' true. Therefore, argument A8's conclusion is correct, but its internal explanation about 'supporting the negation' is incoherent and contradicts its own stated conclusion.",
          "confidence": 0.98,
          "attacks": {
            "A8": 0.9
          }
        }
      ]
    }
  }
}